README.md
setup.py
weixinpayx/__init__.py
weixinpayx/dict2xml.py
weixinpayx/orderquery.py
weixinpayx/refund.py
weixinpayx/refund_decode.py
weixinpayx/refundquery.py
weixinpayx/unifiedorder.py
weixinpayx/wx_utils.py
weixinpayx/xml2dict.py
weixinpayx.egg-info/PKG-INFO
weixinpayx.egg-info/SOURCES.txt
weixinpayx.egg-info/dependency_links.txt
weixinpayx.egg-info/top_level.txt